Metadata-Version: 1.0
Name: photobook
Version: 0.9
Summary: Built photobook with python
Home-page: https://git.opytex.org/lafrite/photobook.git
Author: Benjamin Bertrand
Author-email: benjamin.bertrand@opytex.org
License: UNKNOWN
Platform: UNKNOWN
